<?xml version="1.0" encoding="UTF-8" standalone="yes"?>
<ArrayOfOutline xmlns:xsi="http://www.w3.org/2001/XMLSchema-instance">
	<Outline>
		<Number>1</Number>
		<Title>Será que conhece bem a Deus?</Title>
	</Outline>
	<Outline>
		<Number>2</Number>
		<Title>Será que vai sobreviver aos últimos dias?</Title>
	</Outline>
	<Outline>
		<Number>3</Number>
		<Title>Está a avançar com a organização unida de Jeová?</Title>
	</Outline>
	<Outline>
		<Number>4</Number>
		<Title>Que provas temos de que Deus existe?</Title>
	</Outline>
	<Outline>
		<Number>5</Number>
		<Title>É possível ter uma família feliz!</Title>
	</Outline>
	<Outline>
		<Number>6</Number>
		<Title>O Dilúvio dos dias de Noé e você</Title>
	</Outline>
	<Outline>
		<Number>7</Number>
		<Title>Imite a misericórdia de Jeová</Title>
	</Outline>
	<Outline>
		<Number>8</Number>
		<Title>Viva para fazer a vontade de Deus</Title>
	</Outline>
	<Outline>
		<Number>9</Number>
		<Title>Escute e faça o que a Bíblia diz</Title>
	</Outline>
	<Outline>
		<Number>10</Number>
		<Title>Seja honesto em tudo</Title>
	</Outline>
	<Outline>
		<Number>11</Number>
		<Title>Imite Jesus e não faça parte do mundo</Title>
	</Outline>
	<Outline>
		<Number>12</Number>
		<Title>Deus quer que respeitemos quem tem autoridade</Title>
	</Outline>
	<Outline>
		<Number>13</Number>
		<Title>Qual é o ponto de vista de Deus sobre o sexo e o casamento?</Title>
	</Outline>
	<Outline>
		<Number>14</Number>
		<Title>Um povo puro e limpo honra a Jeová</Title>
	</Outline>
	<Outline>
		<Number>15</Number>
		<Title>'Faça o bem a todos'</Title>
	</Outline>
	<Outline>
		<Number>16</Number>
		<Title>Seja cada vez mais amigo de Jeová</Title>
	</Outline>
	<Outline>
		<Number>17</Number>
		<Title>Glorifique a Deus com tudo o que tem</Title>
	</Outline>
	<Outline>
		<Number>18</Number>
		<Title>Faça de Jeová a sua fortaleza</Title>
	</Outline>
	<Outline>
		<Number>19</Number>
		<Title>Como poderá saber o seu futuro?</Title>
	</Outline>
	<Outline>
		<Number>20</Number>
		<Title>Será que já chegou o tempo de Deus governar o mundo?</Title>
	</Outline>
	<Outline>
		<Number>21</Number>
		<Title>Dê valor ao seu lugar no Reino de Deus</Title>
	</Outline>
	<Outline>
		<Number>22</Number>
		<Title>Está a beneficiar-se das provisões que Jeová lhe dá?</Title>
	</Outline>
	<Outline>
		<Number>23</Number>
		<Title>A vida tem objetivo</Title>
	</Outline>
	<Outline>
		<Number>24</Number>
		<Title>Encontrou "uma pérola de grande valor"?</Title>
	</Outline>
	<Outline>
		<Number>25</Number>
		<Title>Lute contra o espírito do mundo</Title>
	</Outline>
	<Outline>
		<Number>26</Number>
		<Title>Será que você é importante para Deus?</Title>
	</Outline>
	<Outline>
		<Number>27</Number>
		<Title>Como construir um casamento feliz</Title>
	</Outline>
	<Outline>
		<Number>28</Number>
		<Title>Mostre respeito e amor no seu casamento</Title>
	</Outline>
	<Outline>
		<Number>29</Number>
		<Title>As responsabilidades e as recompensas de se ter filhos</Title>
	</Outline>
	<Outline>
		<Number>30</Number>
		<Title>Como melhorar a comunicação na família</Title>
	</Outline>
	<Outline>
		<Number>31</Number>
		<Title>Será que tem consciência da sua necessidade espiritual?</Title>
	</Outline>
	<Outline>
		<Number>32</Number>
		<Title>Como lidar com as ansiedades da vida</Title>
	</Outline>
	<Outline>
		<Number>33</Number>
		<Title>Quando é que vai existir verdadeira justiça?</Title>
	</Outline>
	<Outline>
		<Number>34</Number>
		<Title>Será que você vai ser marcado para sobreviver?</Title>
	</Outline>
	<Outline>
		<Number>35</Number>
		<Title>É possível viver para sempre? O que precisa de fazer?</Title>
	</Outline>
	<Outline>
		<Number>36</Number>
		<Title>Será que esta vida é tudo o que há?</Title>
	</Outline>
	<Outline>
		<Number>37</Number>
		<Title>Será que obedecer a Deus é mesmo a melhor coisa a fazer?</Title>
	</Outline>
	<Outline>
		<Number>38</Number>
		<Title>Como é que você pode sobreviver ao fim do mundo?</Title>
	</Outline>
	<Outline>
		<Number>39</Number>
		<Title>Jesus Cristo vence o mundo - Como e quando?</Title>
	</Outline>
	<Outline>
		<Number>40</Number>
		<Title>Que coisas acontecerão em breve?</Title>
	</Outline>
	<Outline>
		<Number>41</Number>
		<Title>Fiquem parados e vejam como Jeová vos salvará</Title>
	</Outline>
	<Outline>
		<Number>42</Number>
		<Title>Como é que o amor pode vencer o ódio?</Title>
	</Outline>
	<Outline>
		<Number>43</Number>
		<Title>Tudo o que Deus nos pede é para o nosso bem</Title>
	</Outline>
	<Outline>
		<Number>44</Number>
		<Title>Como é que os ensinos de Jesus podem ajudá-lo?</Title>
	</Outline>
	<Outline>
		<Number>45</Number>
		<Title>Continue a andar no caminho que leva à vida</Title>
	</Outline>
	<Outline>
		<Number>46</Number>
		<Title>Fortaleça a sua confiança em Jeová</Title>
	</Outline>
	<Outline>
		<Number>47</Number>
		<Title>'Tenha fé nas boas novas'</Title>
		<Notes>Este esboço não deverá ser usado depois de 1 de abril de 2019 (S-147-19.03)</Notes>
	</Outline>
	<Outline>
		<Number>48</Number>
		<Title>Seja leal a Deus mesmo quando for testado</Title>
	</Outline>
	<Outline>
		<Number>49</Number>
		<Title>Será que um dia a Terra vai ser limpa?</Title>
	</Outline>
	<Outline>
		<Number>50</Number>
		<Title>Como tomar sempre as melhores decisões</Title>
	</Outline>
	<Outline>
		<Number>51</Number>
		<Title>Será que a verdade da Bíblia está a mudar a sua vida?</Title>
	</Outline>
	<Outline>
		<Number>52</Number>
		<Title>Quem é o seu Deus?</Title>
	</Outline>
	<Outline>
		<Number>53</Number>
		<Title>Será que você pensa como Deus?</Title>
	</Outline>
	<Outline>
		<Number>54</Number>
		<Title>Fortaleça a sua fé em Deus e nas suas promessas</Title>
	</Outline>
	<Outline>
		<Number>55</Number>
		<Title>Está a fazer um bom nome perante Deus?</Title>
	</Outline>
	<Outline>
		<Number>56</Number>
		<Title>Um líder em que se pode confiar</Title>
	</Outline>
	<Outline>
		<Number>57</Number>
		<Title>Como suportar perseguição</Title>
	</Outline>
	<Outline>
		<Number>58</Number>
		<Title>Quem são os verdadeiros seguidores de Cristo?</Title>
	</Outline>
	<Outline>
		<Number>59</Number>
		<Title>Colherá o que semear</Title>
	</Outline>
	<Outline>
		<Number>60</Number>
		<Title>Tenha um objetivo na vida</Title>
	</Outline>
	<Outline>
		<Number>61</Number>
		<Title>Nas promessas de quem é que você confia?</Title>
	</Outline>
	<Outline>
		<Number>62</Number>
		<Title>Onde encontrar uma esperança real para o futuro?</Title>
	</Outline>
	<Outline>
		<Number>63</Number>
		<Title>Será que tem espírito evangelizador?</Title>
	</Outline>
	<Outline>
		<Number>64</Number>
		<Title>Será que você ama os prazeres ou a Deus?</Title>
	</Outline>
	<Outline>
		<Number>65</Number>
		<Title>Como cultivar a paz num mundo violento</Title>
	</Outline>
	<Outline>
		<Number>66</Number>
		<Title>Será que você também vai participar na colheita?</Title>
	</Outline>
	<Outline>
		<Number>67</Number>
		<Title>Medite na Bíblia e na criação de Jeová</Title>
	</Outline>
	<Outline>
		<Number>68</Number>
		<Title>'Continuem a perdoar-se uns aos outros liberalmente'</Title>
	</Outline>
	<Outline>
		<Number>69</Number>
		<Title>Porquê mostrar amor abnegado?</Title>
	</Outline>
	<Outline>
		<Number>70</Number>
		<Title>Porque é que Deus merece a sua confiança?</Title>
	</Outline>
	<Outline>
		<Number>71</Number>
		<Title>'Mantenha-se desperto' – Porquê e como?</Title>
	</Outline>
	<Outline>
		<Number>72</Number>
		<Title>O amor identifica os cristãos verdadeiros</Title>
	</Outline>
	<Outline>
		<Number>73</Number>
		<Title>Será que você tem "um coração sábio"?</Title>
	</Outline>
	<Outline>
		<Number>74</Number>
		<Title>Os olhos de Jeová estão em todo o lado</Title>
	</Outline>
	<Outline>
		<Number>75</Number>
		<Title>Mostre que apoia o direito de Jeová governar</Title>
	</Outline>
	<Outline>
		<Number>76</Number>
		<Title>Será que os princípios bíblicos nos podem ajudar a lidar com os problemas atuais?</Title>
	</Outline>
	<Outline>
		<Number>77</Number>
		<Title>"Mostrem sempre hospitalidade"</Title>
	</Outline>
	<Outline>
		<Number>78</Number>
		<Title>Sirva a Jeová com um coração alegre</Title>
	</Outline>
	<Outline>
		<Number>79</Number>
		<Title>Vai escolher ser amigo de Deus?</Title>
	</Outline>
	<Outline>
		<Number>80</Number>
		<Title>Baseia a sua esperança na ciência ou na Bíblia?</Title>
	</Outline>
	<Outline>
		<Number>81</Number>
		<Title>Quem está qualificado para fazer discípulos?</Title>
	</Outline>
	<Outline>
		<Number>82</Number>
		<Title>Será que Jeová e Cristo fazem parte de uma Trindade?</Title>
		<Notes>Este esboço não deverá ser usado depois de 1 de janeiro de 2023 (S-147-22.10)</Notes>
	</Outline>
	<Outline>
		<Number>83</Number>
		<Title>Quando será executado o julgamento da religião?</Title>
	</Outline>
	<Outline>
		<Number>84</Number>
		<Title>Como escapar do destino deste mundo?</Title>
	</Outline>
	<Outline>
		<Number>85</Number>
		<Title>Boas notícias num mundo violento</Title>
	</Outline>
	<Outline>
		<Number>86</Number>
		<Title>Quais são as orações que Deus ouve?</Title>
	</Outline>
	<Outline>
		<Number>87</Number>
		<Title>Qual é a sua relação com Deus?</Title>
	</Outline>
	<Outline>
		<Number>88</Number>
		<Title>Porquê viver de acordo com os padrões da Bíblia?</Title>
	</Outline>
	<Outline>
		<Number>89</Number>
		<Title>Quem tem sede da verdade venha!</Title>
	</Outline>
	<Outline>
		<Number>90</Number>
		<Title>Procure alcançar a verdadeira vida!</Title>
	</Outline>
	<Outline>
		<Number>91</Number>
		<Title>A presença do Messias e o seu domínio</Title>
	</Outline>
	<Outline>
		<Number>92</Number>
		<Title>O papel da religião nos assuntos do mundo</Title>
	</Outline>
	<Outline>
		<Number>93</Number>
		<Title>Desastres naturais - Quando acabarão?</Title>
	</Outline>
	<Outline>
		<Number>94</Number>
		<Title>A religião verdadeira satisfaz as necessidade da sociedade humana</Title>
	</Outline>
	<Outline>
		<Number>95</Number>
		<Title>Não seja enganado pelo ocultismo!</Title>
	</Outline>
	<Outline>
		<Number>96</Number>
		<Title>O que vai acontecer ás religiões?</Title>
	</Outline>
	<Outline>
		<Number>97</Number>
		<Title>Continuemos irrepreensíveis no meio de uma geração pervertida</Title>
	</Outline>
	<Outline>
		<Number>98</Number>
		<Title>"A cena deste mundo está a mudar"</Title>
	</Outline>
	<Outline>
		<Number>99</Number>
		<Title>Porque podemos confiar na Bíblia?</Title>
	</Outline>
	<Outline>
		<Number>100</Number>
		<Title>Como fazer amizades fortes e verdadeiras</Title>
	</Outline>
	<Outline>
		<Number>101</Number>
		<Title>Jeová é o "Grandioso Criador"</Title>
	</Outline>
	<Outline>
		<Number>102</Number>
		<Title>Preste atenção à "palavra profética"</Title>
	</Outline>
	<Outline>
		<Number>103</Number>
		<Title>Pode encontrar-se alegria em servir a Deus</Title>
		<Notes>Este esboço não deverá ser usado depois de 1 de setembro de 2022 (S-147-22.03)</Notes>
	</Outline>
	<Outline>
		<Number>104</Number>
		<Title>Pais, estão a construir com materiais à prova de fogo?</Title>
	</Outline>
	<Outline>
		<Number>105</Number>
		<Title>Somos consolados em todas as nossas tribulações</Title>
	</Outline>
	<Outline>
		<Number>106</Number>
		<Title>Arruinar a Terra provocará retribuição divina</Title>
	</Outline>
	<Outline>
		<Number>107</Number>
		<Title>Será que você está a treinar bem a sua consciência?</Title>
	</Outline>
	<Outline>
		<Number>108</Number>
		<Title>Você pode encarar o futuro com confiança!</Title>
	</Outline>
	<Outline>
		<Number>109</Number>
		<Title>O Reino de Deus está próximo</Title>
	</Outline>
	<Outline>
		<Number>110</Number>
		<Title>Deus vem em primeiro lugar na vida familiar bem-sucedida</Title>
	</Outline>
	<Outline>
		<Number>111</Number>
		<Title>É possível que a humanidade seja completamente curada?</Title>
	</Outline>
	<Outline>
		<Number>112</Number>
		<Title>Como expressar amor num mundo que viola a lei</Title>
		<Notes>Este esboço não deverá ser usado depois de 1 de junho de 2023 (S-147_TPO_202303)</Notes>
	</Outline>
	<Outline>
		<Number>113</Number>
		<Title>Jovens – Como podem ter uma vida feliz?</Title>
	</Outline>
	<Outline>
		<Number>114</Number>
		<Title>Apreço pelas maravilhas da criação de Deus</Title>
	</Outline>
	<Outline>
		<Number>115</Number>
		<Title>Como nos podemos proteger contra os laços de Satanás</Title>
	</Outline>
	<Outline>
		<Number>116</Number>
		<Title>Escolha sabiamente com quem irá associar-se!</Title>
	</Outline>
	<Outline>
		<Number>117</Number>
		<Title>Como vencer o mal com o bem</Title>
	</Outline>
	<Outline>
		<Number>118</Number>
		<Title>Olhemos para os jovens do ponto de vista de Jeová</Title>
	</Outline>
	<Outline>
		<Number>119</Number>
		<Title>Porque é benéfico que os cristãos vivam separados do mundo</Title>
	</Outline>
	<Outline>
		<Number>120</Number>
		<Title>Submeta-se desde já à regência de Deus</Title>
	</Outline>
	<Outline>
		<Number>121</Number>
		<Title>Uma família mundial será salva da destruição</Title>
	</Outline>
	<Outline>
		<Number>122</Number>
		<Title>De onde virá a paz global?</Title>
	</Outline>
	<Outline>
		<Number>123</Number>
		<Title>Os cristãos têm de ser diferentes - porquê?</Title>
	</Outline>
	<Outline>
		<Number>124</Number>
		<Title>Razões para crer que a Bíblia é de autoria divina</Title>
	</Outline>
	<Outline>
		<Number>125</Number>
		<Title>Porque é que a humanidade precisa de um resgate?</Title>
	</Outline>
	<Outline>
		<Number>126</Number>
		<Title>Quem se salvará?</Title>
	</Outline>
	<Outline>
		<Number>127</Number>
		<Title>O que acontece quando morremos?</Title>
	</Outline>
	<Outline>
		<Number>128</Number>
		<Title>Será que o inferno é um lugar de tormento ardente?</Title>
	</Outline>
	<Outline>
		<Number>129</Number>
		<Title>O que é que a Bíblia diz sobre a Trindade?</Title>
	</Outline>
	<Outline>
		<Number>130</Number>
		<Title>A Terra permanecerá para sempre</Title>
	</Outline>
	<Outline>
		<Number>131</Number>
		<Title>Será que o Diabo realmente existe?</Title>
		<Notes>Este esboço não deverá ser usado depois de 1 de setembro de 2023 (S-147_TPO_202303)</Notes>
	</Outline>
	<Outline>
		<Number>132</Number>
		<Title>Ressurreição - a vitória sobre a morte!</Title>
		<Notes>Este esboço não deverá ser usado depois de 1 de setembro de 2023 (S-147_TPO_202308)</Notes>
	</Outline>
	<Outline>
		<Number>133</Number>
		<Title>Será que aquilo em que cremos sobre a nossa origem é importante?</Title>
	</Outline>
	<Outline>
		<Number>134</Number>
		<Title>Devem os cristãos guardar o sábado?</Title>
	</Outline>
	<Outline>
		<Number>135</Number>
		<Title>A santidade da vida e do sangue</Title>
	</Outline>
	<Outline>
		<Number>136</Number>
		<Title>Será que Deus aprova o uso de imagens na adoração?</Title>
	</Outline>
	<Outline>
		<Number>137</Number>
		<Title>Será que os milagres da Biblia realmente ocorreram?</Title>
	</Outline>
	<Outline>
		<Number>138</Number>
		<Title>Viva com bom senso num mundo depravado</Title>
	</Outline>
	<Outline>
		<Number>139</Number>
		<Title>Sabedoria divina num mundo científico</Title>
	</Outline>
	<Outline>
		<Number>140</Number>
		<Title>Quem é realmente Jesus Cristo?</Title>
	</Outline>
	<Outline>
		<Number>141</Number>
		<Title>Quando terão fim os gemidos da criação humana?</Title>
	</Outline>
	<Outline>
		<Number>142</Number>
		<Title>Porquê refugiar-se em Jeová?</Title>
	</Outline>
	<Outline>
		<Number>143</Number>
		<Title>Confie no Deus de todo o consolo</Title>
	</Outline>
	<Outline>
		<Number>144</Number>
		<Title>Uma congregação leal sob a liderança de Cristo</Title>
	</Outline>
	<Outline>
		<Number>145</Number>
		<Title>Quem é semelhante a Jeová, o nosso Deus?</Title>
	</Outline>
	<Outline>
		<Number>146</Number>
		<Title>Use a sua educação para louvar a Jeová</Title>
	</Outline>
	<Outline>
		<Number>147</Number>
		<Title>Confie no poder salvador de Jeová</Title>
	</Outline>
	<Outline>
		<Number>148</Number>
		<Title>Tem o mesmo conceito que Deus sobre a vida?</Title>
	</Outline>
	<Outline>
		<Number>149</Number>
		<Title>O que significa "andar com Deus"?</Title>
	</Outline>
	<Outline>
		<Number>150</Number>
		<Title>Será que este mundo está condenado à destruição?</Title>
	</Outline>
	<Outline>
		<Number>151</Number>
		<Title>Jeová é "um refugio seguro" para o seu povo</Title>
	</Outline>
	<Outline>
		<Number>152</Number>
		<Title>Armagedon — porquê e quando?</Title>
	</Outline>
	<Outline>
		<Number>153</Number>
		<Title>Tenha bem em mente o "atemorizante dia"!</Title>
	</Outline>
	<Outline>
		<Number>154</Number>
		<Title>Os governos humanos são pesados na balança</Title>
	</Outline>
	<Outline>
		<Number>155</Number>
		<Title>Será que já chegou a hora do julgamento de Babilónia?</Title>
	</Outline>
	<Outline>
		<Number>156</Number>
		<Title>O dia do julgamento - tempo de temor ou de esperança?</Title>
	</Outline>
	<Outline>
		<Number>157</Number>
		<Title>Como os verdadeiros cristãos adornam o ensino divino</Title>
	</Outline>
	<Outline>
		<Number>158</Number>
		<Title>Seja corajoso e confie em Jeová</Title>
	</Outline>
	<Outline>
		<Number>159</Number>
		<Title>Como encontrar segurança num mundo perigoso</Title>
	</Outline>
	<Outline>
		<Number>160</Number>
		<Title>Mantenha a sua identidade cristã!</Title>
	</Outline>
	<Outline>
		<Number>161</Number>
		<Title>Porque é que Jesus sofreu e morreu?</Title>
	</Outline>
	<Outline>
		<Number>162</Number>
		<Title>Seja liberto deste mundo em escuridão</Title>
	</Outline>
	<Outline>
		<Number>163</Number>
		<Title>Porque devemos temer o Deus verdadeiro?</Title>
	</Outline>
	<Outline>
		<Number>164</Number>
		<Title>Será que Deus ainda está no controlo?</Title>
	</Outline>
	<Outline>
		<Number>165</Number>
		<Title>De quem são os valores que você preza?</Title>
	</Outline>
	<Outline>
		<Number>166</Number>
		<Title>Como enfrentar o futuro com fé e coragem</Title>
	</Outline>
	<Outline>
		<Number>167</Number>
		<Title>Ajamos sabiamente num mundo insensato</Title>
	</Outline>
	<Outline>
		<Number>168</Number>
		<Title>Sinta-se seguro neste mundo atribulado!</Title>
	</Outline>
	<Outline>
		<Number>169</Number>
		<Title>Porquê orientar-se pela Bíblia?</Title>
	</Outline>
	<Outline>
		<Number>170</Number>
		<Title>Quem está qualificado para governar a humanidade?</Title>
	</Outline>
	<Outline>
		<Number>171</Number>
		<Title>Poderá viver em paz - agora e para sempre!</Title>
	</Outline>
	<Outline>
		<Number>172</Number>
		<Title>Qual é a sua reputação perante Deus?</Title>
	</Outline>
	<Outline>
		<Number>173</Number>
		<Title>Existe uma religião verdadeira do ponto de vista de Deus?</Title>
	</Outline>
	<Outline>
		<Number>174</Number>
		<Title>Quem se qualificará para entrar no novo mundo de Deus?</Title>
	</Outline>
	<Outline>
		<Number>175</Number>
		<Title>O que prova que a Bíblia é autêntica?</Title>
	</Outline>
	<Outline>
		<Number>176</Number>
		<Title>Quando haverá verdadeira paz e segurança?</Title>
	</Outline>
	<Outline>
		<Number>177</Number>
		<Title>Onde encontrar ajuda em tempos de aflição?</Title>
	</Outline>
	<Outline>
		<Number>178</Number>
		<Title>Ande no caminho da integridade</Title>
	</Outline>
	<Outline>
		<Number>179</Number>
		<Title>Rejeite as fantasias do mundo, empenhe-se pelas realidades do Reino</Title>
	</Outline>
	<Outline>
		<Number>180</Number>
		<Title>Porque é que a esperança da ressurreição deve ser real para si?</Title>
	</Outline>
	<Outline>
		<Number>181</Number>
		<Title>Será que já é mais tarde do que imagina?</Title>
	</Outline>
	<Outline>
		<Number>182</Number>
		<Title>O que é que o Reino de Deus está a fazer por nós agora?</Title>
	</Outline>
	<Outline>
		<Number>183</Number>
		<Title>Desvie os seus olhos do que não tem valor</Title>
	</Outline>
	<Outline>
		<Number>184</Number>
		<Title>Será que a morte é o fim de tudo?</Title>
	</Outline>
	<Outline>
		<Number>185</Number>
		<Title>Será que a verdade influencia a sua vida?</Title>
	</Outline>
	<Outline>
		<Number>186</Number>
		<Title>Sirva em união com o povo feliz de Deus</Title>
	</Outline>
	<Outline>
		<Number>187</Number>
		<Title>Porque é que um Deus amoroso permite a maldade?</Title>
	</Outline>
	<Outline>
		<Number>188</Number>
		<Title>Confia em Jeová?</Title>
	</Outline>
	<Outline>
		<Number>189</Number>
		<Title>Andar com Deus traz bênçãos agora e para sempre</Title>
	</Outline>
	<Outline>
		<Number>190</Number>
		<Title>Como se cumprirá a promessa de perfeita felicidade familiar</Title>
	</Outline>
	<Outline>
		<Number>191</Number>
		<Title>Como é que o amor e a fé vencem o mundo</Title>
	</Outline>
	<Outline>
		<Number>192</Number>
		<Title>Está a caminhar na estrada para a vida eterna?</Title>
	</Outline>
	<Outline>
		<Number>193</Number>
		<Title>Em breve, os problemas de hoje serão parte do passado</Title>
	</Outline>
	<Outline>
		<Number>194</Number>
		<Title>Como a sabedoria de Deus nos ajuda</Title>
	</Outline>
	<Outline>
		<Number>195</Number>
		<Title> </Title>
	</Outline>
	<Outline>
		<Number>196</Number>
		<Title> </Title>
	</Outline>
	<Outline>
		<Number>197</Number>
		<Title> </Title>
	</Outline>
	<Outline>
		<Number>198</Number>
		<Title> </Title>
	</Outline>
	<Outline>
		<Number>199</Number>
		<Title> </Title>
	</Outline>
	<Outline>
		<Number>200</Number>
		<Title> </Title>
	</Outline>
</ArrayOfOutline>
